cdcs/RestClient.py
cdcs/VERSION
cdcs/__init__.py
cdcs/aslist.py
cdcs/date_parser.py
cdcs/CDCS/__init__.py
cdcs/CDCS/_blob.py
cdcs/CDCS/_pid.py
cdcs/CDCS/_query.py
cdcs/CDCS/_record.py
cdcs/CDCS/_template.py
cdcs/CDCS/_workspace.py
cdcs/CDCS/_xslt.py
cdcs-0.2.6.dist-info/licenses/LICENSE.TXT
cdcs-0.2.6.dist-info/METADATA
cdcs-0.2.6.dist-info/WHEEL
cdcs-0.2.6.dist-info/top_level.txt
cdcs-0.2.6.dist-info/RECORD
