Metadata-Version: 2.4
Name: cdcs
Version: 0.2.6
Summary: Python API client for performing REST calls to configurable data curation system (CDCS) databases
Home-page: https://github.com/usnistgov/pycdcs
Author: Lucas Hale
Author-email: lucas.hale@nist.gov
Keywords: CDCS,database,rest API,configurable data curation system
Classifier: Development Status :: 4 - Beta
Classifier: Intended Audience :: Science/Research
Classifier: Natural Language :: English
Classifier: Programming Language :: Python :: 3.8
Classifier: Programming Language :: Python :: 3.9
Classifier: Programming Language :: Python :: 3.10
Classifier: Programming Language :: Python :: 3.11
Classifier: Topic :: Scientific/Engineering :: Physics
License-File: LICENSE.TXT
Requires-Dist: requests
Requires-Dist: pandas
Requires-Dist: tqdm
Requires-Dist: ipython
Dynamic: author
Dynamic: author-email
Dynamic: classifier
Dynamic: description
Dynamic: home-page
Dynamic: keywords
Dynamic: license-file
Dynamic: requires-dist
Dynamic: summary
